cymbology/__init__.py
cymbology/_version.py
cymbology/alphanum.py
cymbology/codes.py
cymbology/exceptions.py
cymbology/luhn.py
cymbology/validation.py
cymbology/identifiers/__init__.py
cymbology/identifiers/cusip.py
cymbology/identifiers/isin.py
cymbology/identifiers/sedol.py
cymbology-0.2.3.dist-info/DESCRIPTION.rst
cymbology-0.2.3.dist-info/METADATA
cymbology-0.2.3.dist-info/RECORD
cymbology-0.2.3.dist-info/WHEEL
cymbology-0.2.3.dist-info/metadata.json
cymbology-0.2.3.dist-info/top_level.txt
