Metadata-Version: 2.0
Name: cymbology
Version: 0.2.3
Summary: financial identifier validation.
Home-page: https://github.com/pmart123/cymbology
Author: Philip Martin
Author-email: philip.martin2007@gmail.com
License: BSD
Keywords: finance symbology securities entities entity-resolution
Platform: UNKNOWN
Classifier: Development Status :: 5 - Production/Stable
Classifier: Intended Audience :: Developers
Classifier: Natural Language :: English
Classifier: Programming Language :: Python :: 3.5
Classifier: Programming Language :: Python :: 3.6
Provides-Extra: develop
Requires-Dist: flake8; extra == 'develop'
Requires-Dist: pylint; extra == 'develop'
Provides-Extra: test
Requires-Dist: pytest; extra == 'test'
Requires-Dist: pytest-cov; extra == 'test'
